app.py
targeted_individual-0.0.1.dist-info/METADATA
targeted_individual-0.0.1.dist-info/WHEEL
targeted_individual-0.0.1.dist-info/top_level.txt
targeted_individual-0.0.1.dist-info/RECORD
