Metadata-Version: 2.4
Name: targeted-individual
Version: 0.0.1
Summary: Add your description here
Requires-Python: >=3.10.15
Requires-Dist: aiohttp>=3.12.15
Requires-Dist: bleak>=1.1.0
